{
  "query_id": "635",
  "timestamp": "2025-10-23T09:56:46.875487",
  "model": "AWS-Comprehend-Medical-DetectPHI",
  "aws_config": {
    "region": "us-east-1",
    "api": "DetectPHI",
    "version": "2018-10-30"
  },
  "original_query": "Best treatment options for a 72-year-old female with advanced COPD, admitted to St. John's Hospital on February 15th, 2023, MRN 12345.",
  "ground_truth_phi": "GEOGRAPHIC_LOCATION: St. John's Hospital | DATE: February 15th, 2023 | MEDICAL_RECORD_NUMBER: 12345",
  "ground_truth_phi_count": 3,
  "aws_entities_detected": [
    {
      "text": "72",
      "aws_type": "AGE",
      "hipaa_category": "AGE",
      "category": "PROTECTED_HEALTH_INFORMATION",
      "score": 0.9994620680809021,
      "begin_offset": 29,
      "end_offset": 31
    },
    {
      "text": "St. John's Hospital",
      "aws_type": "ADDRESS",
      "hipaa_category": "GEOGRAPHIC_LOCATION",
      "category": "PROTECTED_HEALTH_INFORMATION",
      "score": 0.993644118309021,
      "begin_offset": 80,
      "end_offset": 99
    },
    {
      "text": "February 15th, 2023",
      "aws_type": "DATE",
      "hipaa_category": "DATE",
      "category": "PROTECTED_HEALTH_INFORMATION",
      "score": 0.9991298317909241,
      "begin_offset": 103,
      "end_offset": 122
    },
    {
      "text": "12345",
      "aws_type": "ID",
      "hipaa_category": "UNIQUE_IDENTIFIER",
      "category": "PROTECTED_HEALTH_INFORMATION",
      "score": 0.15833403170108795,
      "begin_offset": 128,
      "end_offset": 133
    }
  ],
  "leak_detection": {
    "leaked_phi_count": 0,
    "leaked_phi_details": [],
    "status": "NO_LEAK"
  },
  "metrics": {
    "total_phi_entities": 3,
    "successfully_detected": 3,
    "leaked_failures": 0,
    "total_detected": 4,
    "true_positives": 3,
    "recall": "1.0000",
    "precision": "0.7500",
    "f1_score": "0.8571"
  },
  "error": null,
  "confidence_threshold": 0.0,
  "aws_entities_original_count": 4,
  "aws_entities_filtered_count": 4
}